server/__init__.py
server/server.py
server/common/__init__.py
server/common/descriptors.py
server/common/errors.py
server/common/helper.py
server/common/log_decorator.py
server/common/metacls.py
server/common/utils.py
server/common/variables.py
server/logs/__init__.py
server/logs/client_log_config.py
server/logs/server_log_config.py
server/server_app/__init__.py
server/server_app/add_user.py
server/server_app/config_window.py
server/server_app/core.py
server/server_app/main_window.py
server/server_app/remove_user.py
server/server_app/server_db.py
server/server_app/stat_window.py
server/unit_tests/__init__.py
jimm_chat_server-0.1.1.dist-info/METADATA
jimm_chat_server-0.1.1.dist-info/WHEEL
jimm_chat_server-0.1.1.dist-info/top_level.txt
jimm_chat_server-0.1.1.dist-info/RECORD
